Metadata-Version: 2.1
Name: polypal
Version: 1.0.0
Summary: A Python package to assist with parameterization and construction of all-atomistic polymer simulations
Home-page: https://github.com/warndorf/polypal
Author: Molly C. Warndorf
Author-email: warndorf@mit.edu
License-File: LICENSE
